speakNextcordBot/__init__.py
speakNextcordBot/init_cog.py
speakNextcordBot/cogs/__init__.py
speakNextcordBot/cogs/message.py
speakNextcordBot/modal/__init__.py
speakNextcordBot/modal/replyModal.py
speakNextcordBot/modal/speakModal.py
speakNextcordBot/modal/updateModal.py
speakNextcordBot/utils/__init__.py
speakNextcordBot/utils/message.py
speaknextcordbot-1.1.2.dist-info/licenses/LICENSE
speaknextcordbot-1.1.2.dist-info/METADATA
speaknextcordbot-1.1.2.dist-info/WHEEL
speaknextcordbot-1.1.2.dist-info/top_level.txt
speaknextcordbot-1.1.2.dist-info/RECORD
