Metadata-Version: 2.4
Name: SpeakNextcordBot
Version: 1.1.2
Summary: A python package for adding speak interaction slash command to a Nextcord bot
Home-page: https://github.com/Rs-appez/interaction_discord_bot
Author: Appez
Author-email: appez@appez.cafe
License: GPL-3.0-only
Keywords: discord bot slash_command interaction speak
Classifier: Programming Language :: Python :: 3
Classifier: Operating System :: OS Independent
Classifier: Development Status :: 5 - Production/Stable
Classifier: Intended Audience :: Developers
Classifier: Topic :: Software Development :: Libraries :: Python Modules
Requires-Python: >=3.12
License-File: LICENSE
Requires-Dist: nextcord
Dynamic: author
Dynamic: author-email
Dynamic: classifier
Dynamic: description
Dynamic: description-content-type
Dynamic: home-page
Dynamic: keywords
Dynamic: license
Dynamic: license-file
Dynamic: requires-dist
Dynamic: requires-python
Dynamic: summary
